COPYING
MANIFEST.in
README.rst
mprof.py
setup.py
cglacet_memory_profiler.egg-info/PKG-INFO
cglacet_memory_profiler.egg-info/SOURCES.txt
cglacet_memory_profiler.egg-info/dependency_links.txt
cglacet_memory_profiler.egg-info/entry_points.txt
cglacet_memory_profiler.egg-info/requires.txt
cglacet_memory_profiler.egg-info/top_level.txt
memory_profiler/__init__.py
memory_profiler/__main__.py
memory_profiler/_async.py
memory_profiler/code_map.py
memory_profiler/common.py
memory_profiler/line_profiler.py
memory_profiler/utils.py
test/test_as.py
test/test_async.py
test/test_exception.py
test/test_exit_code.py
test/test_func.py
test/test_gen.py
test/test_global.py
test/test_import.py
test/test_loop.py
test/test_loop_decorated.py
test/test_memory_usage.py
test/test_mprof.py
test/test_mprofile.py
test/test_nested.py
test/test_precision_command_line.py
test/test_precision_import.py
test/test_stream_unicode.py
test/test_tracemalloc.py
test/test_unicode.py