Metadata-Version: 1.1
Name: cglacet-memory-profiler
Version: 0.57.0
Summary: A module for monitoring memory usage of a python program
Home-page: https://github.com/pythonprofilers/memory_profiler
Author: Fabian Pedregosa
Author-email: f@bianp.net
License: BSD
Platform: UNKNOWN
Classifier: Development Status :: 5 - Production/Stable
Classifier: Intended Audience :: Science/Research
Classifier: Intended Audience :: Developers
Classifier: License :: OSI Approved :: BSD License
Classifier: Programming Language :: Python
Classifier: Programming Language :: Python :: 2
Classifier: Programming Language :: Python :: 2.6
Classifier: Programming Language :: Python :: 2.7
Classifier: Programming Language :: Python :: 3
Classifier: Programming Language :: Python :: 3.2
Classifier: Programming Language :: Python :: 3.3
Classifier: Topic :: Software Development
Classifier: Operating System :: POSIX
Classifier: Operating System :: Unix
